[{"body": [{"type": "know-cube-select", "imgSrc": "", "title": "选一选，圆柱体是那个形状？", "list": [{"src": "v2/通用/基本立体图形/长方体_2.svg"}, {"src": "v2/通用/基本立体图形/圆柱体_1.svg"}]}], "answers": [1], "resource": "resource", "explain": "explain", "knowledges": ["认识圆柱体"], "level": "1", "type": "选择", "number": "1-6-3-02"}, {"body": [{"type": "know-cube-select", "imgSrc": "", "title": "选一选，圆柱体是那个形状？", "list": [{"src": "v2/通用/基本立体图形/长方体_5.svg"}, {"src": "v2/通用/基本立体图形/圆柱体_3.svg"}]}], "answers": [1], "resource": "resource", "explain": "explain", "knowledges": ["认识圆柱体"], "level": "1", "type": "选择", "number": "1-6-3-02"}, {"body": [{"type": "know-cube-select", "imgSrc": "", "title": "选一选，圆柱体是那个形状？", "list": [{"src": "v2/通用/基本立体图形/圆锥体_1.svg"}, {"src": "v2/通用/基本立体图形/圆柱体_3.svg"}]}], "answers": [1], "resource": "resource", "explain": "explain", "knowledges": ["认识圆柱体"], "level": "1", "type": "选择", "number": "1-6-3-02"}, {"body": [{"type": "know-cube-select", "imgSrc": "", "title": "选一选，圆柱体是那个形状？", "list": [{"src": "v2/通用/基本立体图形/圆柱体_3.svg"}, {"src": "v2/通用/基本立体图形/球体_3.svg"}]}], "answers": [0], "resource": "resource", "explain": "explain", "knowledges": ["认识圆柱体"], "level": "1", "type": "选择", "number": "1-6-3-02"}, {"body": [{"type": "know-cube-select", "imgSrc": "", "title": "选一选，圆柱体是那个形状？", "list": [{"src": "v2/通用/基本立体图形/圆柱体_3.svg"}, {"src": "v2/通用/基本立体图形/正方体_2.svg"}]}], "answers": [0], "resource": "resource", "explain": "explain", "knowledges": ["认识圆柱体"], "level": "1", "type": "选择", "number": "1-6-3-02"}, {"body": [{"type": "know-cube-select", "imgSrc": "", "title": "选一选，圆柱体是那个形状？", "list": [{"src": "v2/通用/基本立体图形/长方体_2.svg"}, {"src": "v2/通用/基本立体图形/圆柱体_1.svg"}]}], "answers": [1], "resource": "resource", "explain": "explain", "knowledges": ["认识圆柱体"], "level": "1", "type": "选择", "number": "1-6-3-02"}]